par/__init__.py
par/checkout.py
par/cli.py
par/core.py
par/initialization.py
par/operations.py
par/test_checkout.py
par/test_initialization.py
par/utils.py
par/workspace.py
par_cli-0.1.2.dist-info/WHEEL
par_cli-0.1.2.dist-info/entry_points.txt
par_cli-0.1.2.dist-info/METADATA
par_cli-0.1.2.dist-info/RECORD
