Metadata-Version: 2.3
Name: par-cli
Version: 0.1.2
Summary: CLI for parallel development workflows with isolated Git worktrees and tmux sessions, tailored for agentic coding.
Author: Victor
Author-email: Victor <vimota@gmail.com>
Requires-Dist: typer
Requires-Dist: pyyaml
Requires-Dist: pytest ; extra == 'dev'
Requires-Dist: ruff ; extra == 'dev'
Requires-Dist: pre-commit ; extra == 'dev'
Requires-Dist: build ; extra == 'dev'
Requires-Python: >=3.12
Provides-Extra: dev
